pons/__init__.py
pons/client.py
pons/errors.py
pons/models.py
pons.py-1.1.1.dist-info/LICENSE.txt
pons.py-1.1.1.dist-info/METADATA
pons.py-1.1.1.dist-info/WHEEL
pons.py-1.1.1.dist-info/top_level.txt
pons.py-1.1.1.dist-info/RECORD
