Metadata-Version: 2.1
Name: pons.py
Version: 1.1.1
Summary: An API wrapper for the PONS dictionary
Home-page: https://github.com/Dorukyum/pons.py
Author: Dorukyum
License: MIT
Project-URL: Source, https://github.com/Dorukyum/pons.py
Keywords: API,dictionary
Classifier: License :: OSI Approved :: MIT License
Classifier: Programming Language :: Python :: 3
License-File: LICENSE.txt
Requires-Dist: requests
